[{"__symbolic":"module","version":3,"metadata":{"AnimationGroupPlayer":{"__symbolic":"select","expression":{"__symbolic":"reference","module":"@angular/core","name":"___core_private__"},"member":"AnimationGroupPlayer"},"NoOpAnimationPlayer":{"__symbolic":"select","expression":{"__symbolic":"reference","module":"@angular/core","name":"___core_private__"},"member":"NoOpAnimationPlayer"},"TransitionEngine":{"__symbolic":"select","expression":{"__symbolic":"reference","module":"@angular/core","name":"___core_private__"},"member":"TransitionEngine"}}},{"__symbolic":"module","version":1,"metadata":{"AnimationGroupPlayer":{"__symbolic":"select","expression":{"__symbolic":"reference","module":"@angular/core","name":"___core_private__"},"member":"AnimationGroupPlayer"},"NoOpAnimationPlayer":{"__symbolic":"select","expression":{"__symbolic":"reference","module":"@angular/core","name":"___core_private__"},"member":"NoOpAnimationPlayer"},"TransitionEngine":{"__symbolic":"select","expression":{"__symbolic":"reference","module":"@angular/core","name":"___core_private__"},"member":"TransitionEngine"}}}]